multichain_explorer/__init__.py
multichain_explorer/conftest.py
multichain_explorer/src/__init__.py
multichain_explorer/src/models/__init__.py
multichain_explorer/src/models/blockchains.py
multichain_explorer/src/models/provider_models/__init__.py
multichain_explorer/src/models/provider_models/address.py
multichain_explorer/src/models/provider_models/block.py
multichain_explorer/src/models/provider_models/summary.py
multichain_explorer/src/models/provider_models/transaction.py
multichain_explorer/src/models/provider_options.py
multichain_explorer/src/models/resource_types.py
multichain_explorer/src/providers/__init__.py
multichain_explorer/src/providers/ada/__init__.py
multichain_explorer/src/providers/ada/ada_provider.py
multichain_explorer/src/providers/algo/__init__.py
multichain_explorer/src/providers/algo/algo_provider.py
multichain_explorer/src/providers/btc/__init__.py
multichain_explorer/src/providers/btc/btc_provider.py
multichain_explorer/src/providers/eth/__init__.py
multichain_explorer/src/providers/eth/eth_provider.py
multichain_explorer/src/providers/luna/__init__.py
multichain_explorer/src/providers/luna/luna_provider.py
multichain_explorer/src/providers/provider.py
multichain_explorer/src/providers/provider_factory.py
multichain_explorer/src/services/__init__.py
multichain_explorer/src/services/coinmarketcap_service.py
multichain_explorer/src/services/fetch_service.py
multichain_explorer/src/validators/__init__.py
multichain_explorer/src/validators/ada/__init__.py
multichain_explorer/src/validators/ada/ada_validator.py
multichain_explorer/src/validators/algo/__init__.py
multichain_explorer/src/validators/algo/algo_validator.py
multichain_explorer/src/validators/btc/__init__.py
multichain_explorer/src/validators/btc/btc_validator.py
multichain_explorer/src/validators/eth/__init__.py
multichain_explorer/src/validators/eth/eth_validator.py
multichain_explorer/src/validators/luna/__init__.py
multichain_explorer/src/validators/luna/luna_validator.py
multichain_explorer-0.1.8.dist-info/LICENSE
multichain_explorer-0.1.8.dist-info/WHEEL
multichain_explorer-0.1.8.dist-info/METADATA
multichain_explorer-0.1.8.dist-info/RECORD
