Metadata-Version: 2.1
Name: multichain-explorer
Version: 0.1.8
Summary: A simple package to explore multiple blockchains in an homogeneous way
Author: sdominguez894
Author-email: sdominguez894@gmail.com
Requires-Python: >=3.10,<4.0
Classifier: Programming Language :: Python :: 3
Classifier: Programming Language :: Python :: 3.10
Requires-Dist: blockfrost-python (>=0.4.3,<0.5.0)
Requires-Dist: cryptos (>=1.36,<2.0)
Requires-Dist: py-algorand-sdk (>=1.11.0,<2.0.0)
Requires-Dist: terra-sdk (>=2.0.5,<3.0.0)
Requires-Dist: web3 (>=5.28,<6.0)
